shinepy/__init__.py
shinepy/beam.py
shinepy/helper.py
shinepy/mesh.py
shinepy/radiation.py
shinepy/undulator.py
shinepy/wavefront.py
shinepy-0.0.0.dist-info/licenses/LICENSE
shinepy-0.0.0.dist-info/METADATA
shinepy-0.0.0.dist-info/WHEEL
shinepy-0.0.0.dist-info/top_level.txt
shinepy-0.0.0.dist-info/RECORD
