Metadata-Version: 2.4
Name: shinepy
Version: 0.0.0
Summary: A shining example Python package
Author-email: Antoine Chapelain <atc93@cornell.edu>
License-Expression: MIT
License-File: LICENSE
Dynamic: license-file
